{
	"name": "",
	"parameters": {
		"v_bind_id": {
			"name": "v_bind_id",
			"type": {
				"name": "varchar2"
			},
			"isOut": false
		},
		"v_error_code": {
			"name": "v_error_code",
			"type": {
				"name": "number"
			},
			"isOut": false
		},
		"v_result_msg": {
			"name": "v_result_msg",
			"type": {
				"name": "varchar2"
			},
			"isOut": false
		},
		"v_up_order_no": {
			"name": "v_up_order_no",
			"type": {
				"name": "varchar2"
			},
			"isOut": false
		},
		"v_out_code": {
			"name": "v_out_code",
			"type": {
				"name": "number"
			},
			"isOut": true
		},
		"v_out_msg": {
			"name": "v_out_msg",
			"type": {
				"name": "varchar2"
			},
			"isOut": true
		},
		"v_out_json": {
			"name": "v_out_json",
			"type": {
				"name": "varchar2"
			},
			"isOut": true
		}
	}
}