{
	"name": "fcSmsRecord",
	"description": "",
	"columns": {
		"smsNo": {
			"name": "smsNo",
			"description": "编号",
			"type": {
				"name": "varchar2",
				"length": 32
			},
			"nullable": false,
			"defaltValue": null
		},
		"downChannelNo": {
			"name": "downChannelNo",
			"description": "下游渠道编号",
			"type": {
				"name": "varchar2",
				"length": 32
			},
			"nullable": false,
			"defaltValue": null
		},
		"downOrderNo": {
			"name": "downOrderNo",
			"description": "下游订单号",
			"type": {
				"name": "varchar2",
				"length": 32
			},
			"nullable": false,
			"defaltValue": null
		},
		"productNo": {
			"name": "productNo",
			"description": "产品编号",
			"type": {
				"name": "varchar2",
				"length": 32
			},
			"nullable": false,
			"defaltValue": null
		},
		"phone": {
			"name": "phone",
			"description": "手机号",
			"type": {
				"name": "varchar2",
				"length": 32
			},
			"nullable": false,
			"defaltValue": null
		},
		"carrierNo": {
			"name": "carrierNo",
			"description": "运营商",
			"type": {
				"name": "varchar2",
				"length": 32
			},
			"nullable": false,
			"defaltValue": null
		},
		"provinceNo": {
			"name": "provinceNo",
			"description": "省份",
			"type": {
				"name": "varchar2",
				"length": 32
			},
			"nullable": false,
			"defaltValue": null
		},
		"cityNo": {
			"name": "cityNo",
			"description": "城市",
			"type": {
				"name": "varchar2",
				"length": 32
			},
			"nullable": false,
			"defaltValue": null
		},
		"upChannelNo": {
			"name": "upChannelNo",
			"description": "上游渠道",
			"type": {
				"name": "varchar2",
				"length": 32
			},
			"nullable": false,
			"defaltValue": null
		},
		"upProductNo": {
			"name": "upProductNo",
			"description": "上游产品编号",
			"type": {
				"name": "varchar2",
				"length": 32
			},
			"nullable": false,
			"defaltValue": null
		},
		"upAccountId": {
			"name": "upAccountId",
			"description": "上游帐号id",
			"type": {
				"name": "number"
			},
			"nullable": false,
			"defaltValue": null
		},
		"upProductId": {
			"name": "upProductId",
			"description": "上游产品id",
			"type": {
				"name": "number"
			},
			"nullable": false,
			"defaltValue": null
		},
		"scriptId": {
			"name": "scriptId",
			"description": "脚本id",
			"type": {
				"name": "number"
			},
			"nullable": false,
			"defaltValue": null
		},
		"apiUrl": {
			"name": "apiUrl",
			"description": "接口地址",
			"type": {
				"name": "varchar2",
				"length": 256
			},
			"nullable": false,
			"defaltValue": null
		},
		"status": {
			"name": "status",
			"description": "状态",
			"type": {
				"name": "number"
			},
			"nullable": false,
			"defaltValue": 20
		},
		"msg": {
			"name": "msg",
			"description": "结果消息",
			"type": {
				"name": "varchar2",
				"length": 128
			},
			"nullable": false,
			"defaltValue": null
		},
		"createTime": {
			"name": "createTime",
			"description": "创建时间",
			"type": {
				"name": "date"
			},
			"nullable": false,
			"defaltValue": "sysdate"
		},
		"cookie": {
			"name": "cookie",
			"description": "cookie",
			"type": {
				"name": "varchar2",
				"length": 512
			},
			"nullable": false,
			"defaltValue": null
		},
		"ip": {
			"name": "ip",
			"description": "ip",
			"type": {
				"name": "varchar2",
				"length": 32
			},
			"nullable": false,
			"defaltValue": null
		}
	},
	"rawName": "FC_SMS_RECORD"
}