{
	"name": "fd_f_bank_fund_add_t",
	"parameters": {
		"v_bank_account_id": {
			"name": "v_bank_account_id",
			"type": {
				"name": "number"
			},
			"isOut": false
		},
		"v_amount": {
			"name": "v_amount",
			"type": {
				"name": "number"
			},
			"isOut": false
		},
		"v_change_type": {
			"name": "v_change_type",
			"type": {
				"name": "number"
			},
			"isOut": false
		},
		"v_use_type": {
			"name": "v_use_type",
			"type": {
				"name": "number"
			},
			"isOut": false
		},
		"v_create_user": {
			"name": "v_create_user",
			"type": {
				"name": "varchar2"
			},
			"isOut": false
		},
		"v_create_time": {
			"name": "v_create_time",
			"type": {
				"name": "varchar2"
			},
			"isOut": false
		},
		"v_link_channel_no": {
			"name": "v_link_channel_no",
			"type": {
				"name": "varchar2"
			},
			"isOut": false
		},
		"v_link_account_id": {
			"name": "v_link_account_id",
			"type": {
				"name": "varchar2"
			},
			"isOut": false
		},
		"v_memo": {
			"name": "v_memo",
			"type": {
				"name": "varchar2"
			},
			"isOut": false
		},
		"v_record_no": {
			"name": "v_record_no",
			"type": {
				"name": "varchar2"
			},
			"isOut": false
		}
	},
	"returnType": "varchar2"
}